<annotation>
	<folder>small_train</folder>
	<filename>M0122.jpg</filename>
	<path>/Users/apple/PycharmProjects/yolo_practice/img_data/small_train/M0122.jpg</path>
	<source>
		<database>Unknown</database>
	</source>
	<size>
		<width>224</width>
		<height>224</height>
		<depth>1</depth>
	</size>
	<segmented>0</segmented>
	<object>
		<name>1</name>
		<pose>Unspecified</pose>
		<truncated>0</truncated>
		<difficult>0</difficult>
		<bndbox>
			<xmin>38</xmin>
			<ymin>27</ymin>
			<xmax>57</xmax>
			<ymax>78</ymax>
		</bndbox>
	</object>
	<object>
		<name>1</name>
		<pose>Unspecified</pose>
		<truncated>0</truncated>
		<difficult>0</difficult>
		<bndbox>
			<xmin>145</xmin>
			<ymin>9</ymin>
			<xmax>154</xmax>
			<ymax>23</ymax>
		</bndbox>
	</object>
	<object>
		<name>6</name>
		<pose>Unspecified</pose>
		<truncated>0</truncated>
		<difficult>0</difficult>
		<bndbox>
			<xmin>34</xmin>
			<ymin>167</ymin>
			<xmax>63</xmax>
			<ymax>209</ymax>
		</bndbox>
	</object>
	<object>
		<name>8</name>
		<pose>Unspecified</pose>
		<truncated>0</truncated>
		<difficult>0</difficult>
		<bndbox>
			<xmin>140</xmin>
			<ymin>129</ymin>
			<xmax>170</xmax>
			<ymax>180</ymax>
		</bndbox>
	</object>
</annotation>
